devtools/__init__.py
devtools/__main__.py
devtools/ansi.py
devtools/debug.py
devtools/prettier.py
devtools/py.typed
devtools/pytest_plugin.py
devtools/timer.py
devtools/utils.py
devtools/version.py
devtools-0.12.1.dist-info/METADATA
devtools-0.12.1.dist-info/WHEEL
devtools-0.12.1.dist-info/entry_points.txt
devtools-0.12.1.dist-info/licenses/LICENSE
devtools-0.12.1.dist-info/RECORD
