Metadata-Version: 2.1
Name: devtools
Version: 0.12.1
Summary: Python's missing debug print command, and more.
Project-URL: Homepage, https://github.com/samuelcolvin/python-devtools
Project-URL: Documentation, https://python-devtools.helpmanual.io
Project-URL: Funding, https://github.com/sponsors/samuelcolvin
Project-URL: Source, https://github.com/samuelcolvin/python-devtools
Project-URL: Changelog, https://github.com/samuelcolvin/python-devtools/releases
Author-email: Samuel Colvin <s@muelcolvin.com>
License: The MIT License (MIT)
License-File: LICENSE
Classifier: Development Status :: 5 - Production/Stable
Classifier: Environment :: Console
Classifier: Environment :: MacOS X
Classifier: Intended Audience :: Developers
Classifier: Intended Audience :: Education
Classifier: Intended Audience :: Information Technology
Classifier: Intended Audience :: Science/Research
Classifier: Intended Audience :: System Administrators
Classifier: License :: OSI Approved :: MIT License
Classifier: Operating System :: POSIX :: Linux
Classifier: Operating System :: Unix
Classifier: Programming Language :: Python :: 3 :: Only
Classifier: Programming Language :: Python :: 3.7
Classifier: Programming Language :: Python :: 3.8
Classifier: Programming Language :: Python :: 3.9
Classifier: Programming Language :: Python :: 3.10
Classifier: Programming Language :: Python :: 3.11
Classifier: Topic :: Internet
Classifier: Topic :: Software Development :: Libraries :: Python Modules
Classifier: Typing :: Typed
Requires-Python: >=3.7
Requires-Dist: asttokens<3.0.0,>=2.0.0
Requires-Dist: executing>=1.1.1
Requires-Dist: pygments>=2.15.0
Provides-Extra: pygments
